setup.py
pylichess/__init__.py
pylichess.egg-info/PKG-INFO
pylichess.egg-info/SOURCES.txt
pylichess.egg-info/dependency_links.txt
pylichess.egg-info/requires.txt
pylichess.egg-info/top_level.txt