Metadata-Version: 1.0
Name: pylichess
Version: 0.2
Summary: Python wrapper for the lichess.com api.
Home-page: UNKNOWN
Author: Camden Clark <camdenclark2012@gmail.com>
Author-email: camdenclark2012@gmail.com
License: MIT
Keywords: lichess,chess
Platform: UNKNOWN
